odoo10_addon_mail_inline_css-10.0.1.0.1-py3.8-nspkg.pth
odoo/addons/mail_inline_css/README.rst
odoo/addons/mail_inline_css/__init__.py
odoo/addons/mail_inline_css/__manifest__.py
odoo/addons/mail_inline_css/i18n/de.po
odoo/addons/mail_inline_css/i18n/es.po
odoo/addons/mail_inline_css/i18n/es_MX.po
odoo/addons/mail_inline_css/i18n/fr.po
odoo/addons/mail_inline_css/i18n/hr.po
odoo/addons/mail_inline_css/i18n/it.po
odoo/addons/mail_inline_css/i18n/mail_inline_css.pot
odoo/addons/mail_inline_css/i18n/nl_NL.po
odoo/addons/mail_inline_css/i18n/zh_CN.po
odoo/addons/mail_inline_css/models/__init__.py
odoo/addons/mail_inline_css/models/mail.py
odoo/addons/mail_inline_css/static/description/icon.png
odoo10_addon_mail_inline_css-10.0.1.0.1.dist-info/METADATA
odoo10_addon_mail_inline_css-10.0.1.0.1.dist-info/WHEEL
odoo10_addon_mail_inline_css-10.0.1.0.1.dist-info/namespace_packages.txt
odoo10_addon_mail_inline_css-10.0.1.0.1.dist-info/top_level.txt
odoo10_addon_mail_inline_css-10.0.1.0.1.dist-info/RECORD
